proset/__init__.py
proset/model.py
proset/set_manager.py
proset/shared.py
proset/benchmarks/__init__.py
proset/benchmarks/auxiliary.py
proset/benchmarks/reference.py
proset/benchmarks/samples.py
proset/objectives/__init__.py
proset/objectives/np_classifier_objective.py
proset/objectives/np_objective.py
proset/objectives/objective.py
proset/objectives/shared_classifier.py
proset/objectives/tf_classifier_objective.py
proset/objectives/tf_objective.py
proset/utility/__init__.py
proset/utility/fit.py
proset/utility/other.py
proset/utility/write.py
proset/utility/plots/__init__.py
proset/utility/plots/explore.py
proset/utility/plots/explore_classifier.py
proset/utility/plots/search.py
proset/utility/plots/shared.py
proset-0.6.1.dist-info/LICENSE
proset-0.6.1.dist-info/METADATA
proset-0.6.1.dist-info/WHEEL
proset-0.6.1.dist-info/top_level.txt
proset-0.6.1.dist-info/RECORD
