Metadata-Version: 2.1
Name: proset
Version: 0.6.1
Summary: Prototype set models for supervised learning
Home-page: https://github.com/NRuf77/proset
Author: Nikolaus Ruf
Author-email: nikolaus.ruf@t-online.de
Classifier: Development Status :: 4 - Beta
Classifier: Intended Audience :: Science/Research
Classifier: License :: OSI Approved :: MIT License
Classifier: Programming Language :: Python :: 3
Classifier: Topic :: Scientific/Engineering :: Artificial Intelligence
Requires-Python: >=3.10
License-File: LICENSE
Requires-Dist: matplotlib<3.9,>=3.8.3
Requires-Dist: numpy>=1.26.4
Requires-Dist: pandas>=2.2.1
Requires-Dist: scipy>=1.12.0
Requires-Dist: scikit-learn>=1.4.1.post1
Requires-Dist: statsmodels>=0.14.1
Requires-Dist: xlsxwriter>=3.1.9
Provides-Extra: benchmarks
Requires-Dist: mnist>=0.2.2; extra == "benchmarks"
Requires-Dist: psutil>=5.9.8; extra == "benchmarks"
Requires-Dist: shap>=0.44.0; extra == "benchmarks"
Requires-Dist: xgboost>=2.0.3; extra == "benchmarks"
Provides-Extra: development
Requires-Dist: coverage>=7.4.3; extra == "development"
Requires-Dist: ipython>=8.22.1; extra == "development"
Requires-Dist: pylint>=3.0.4; extra == "development"
Requires-Dist: twine>=5.0.0; extra == "development"
Provides-Extra: tensorflow
Requires-Dist: tensorflow>=2.15.0; extra == "tensorflow"
